{"cameraMode":{"drawMode":0,"name":"Shaded","section":"Shading Mode"},"sceneLighting":true,"audioPlay":false,"sceneViewState":{"showFog":true,"showMaterialUpdate":false,"showSkybox":true,"showFlares":true,"showImageEffects":true,"showParticleSystems":true},"in2DMode":false,"pivot":{"x":2.6445679664611818,"y":-1.069730281829834,"z":-3.1810355186462404},"rotation":{"x":0.3377631902694702,"y":0.228018656373024,"z":-0.08470652252435684,"w":0.9092592000961304},"size":6.503473281860352,"orthographic":false}